doomarena/utils.py
doomarena/core/__init__.py
doomarena/core/agent_defenses/__init__.py
doomarena/core/agent_defenses/base.py
doomarena/core/agent_defenses/llamaguard.py
doomarena/core/agent_defenses/llamaguard_api.py
doomarena/core/agent_defenses/llamaguard_utils.py
doomarena/core/agent_defenses/llamaguard_v3.py
doomarena/core/agent_defenses/llmjudge.py
doomarena/core/agent_defenses/prompted_gpt.py
doomarena/core/agent_defenses/promptguard.py
doomarena/core/agent_defenses/safe_completion_gateway.py
doomarena/core/attack_config/__init__.py
doomarena/core/attack_config/attack_config.py
doomarena/core/attack_config/get_attack_config.py
doomarena/core/attack_config/register_attack_config.py
doomarena/core/attack_gateways/__init__.py
doomarena/core/attack_gateways/attack_gateway.py
doomarena/core/attack_gateways/get_attack_gateway.py
doomarena/core/attack_gateways/register_attack_gateway.py
doomarena/core/attacks/__init__.py
doomarena/core/attacks/adversarial_user_agent_attack.py
doomarena/core/attacks/attacks.py
doomarena/core/attacks/fixed_injection_attack.py
doomarena/core/attacks/fixed_injection_sequence_attacks.py
doomarena/core/attacks/get_attacks.py
doomarena/core/attacks/register_attacks.py
doomarena/core/filters/__init__.py
doomarena/core/filters/always_true_filter.py
doomarena/core/success_filters/__init__.py
doomarena/core/success_filters/always_true_success_filter.py
doomarena/core/success_filters/utils/__init__.py
doomarena/core/success_filters/utils/spawn_server.py
doomarena/demo/break_me_agent.py
doomarena-0.0.4.dist-info/METADATA
doomarena-0.0.4.dist-info/WHEEL
doomarena-0.0.4.dist-info/top_level.txt
doomarena-0.0.4.dist-info/RECORD
